{"date_modified":"2025-01-23T07:19:55","result":{"4985":{"dead_cross_near":0,"golden_cross_near":0,"dead_cross":1,"price":5050,"end_date":"2025-01-23T06:30:00","golden_cross":0},"5915":{"golden_cross_near":94.8148148148147,"dead_cross":0,"price":1585,"end_date":"2025-01-23T06:30:00","golden_cross":1,"dead_cross_near":0},"8609":{"golden_cross_near":0,"dead_cross":1,"price":625,"golden_cross":0,"end_date":"2025-01-23T06:30:00","dead_cross_near":96.9037037037037},"2198":{"dead_cross_near":0,"golden_cross":1,"end_date":"2025-01-23T06:30:00","price":780,"dead_cross":0,"golden_cross_near":67.0222222222223},"2270":{"dead_cross_near":0,"golden_cross_near":0,"dead_cross":1,"price":2564,"golden_cross":0,"end_date":"2025-01-23T06:30:00"},"2804":{"dead_cross_near":30.9777777777779,"golden_cross_near":0,"dead_cross":1,"price":1722,"end_date":"2025-01-23T06:30:00","golden_cross":0},"8153":{"price":3445,"end_date":"2025-01-23T06:30:00","golden_cross":0,"golden_cross_near":0,"dead_cross":1,"dead_cross_near":0},"9008":{"dead_cross_near":69.0814814814813,"price":3733,"golden_cross":0,"end_date":"2025-01-23T06:30:00","golden_cross_near":0,"dead_cross":1},"9900":{"dead_cross_near":48.637037037037,"golden_cross_near":0,"dead_cross":1,"price":1710,"golden_cross":0,"end_date":"2025-01-23T06:30:00"},"8133":{"golden_cross_near":0,"dead_cross":1,"price":1548,"golden_cross":0,"end_date":"2025-01-23T06:30:00","dead_cross_near":37.4222222222223},"8511":{"price":1971,"end_date":"2025-01-23T06:30:00","golden_cross":0,"golden_cross_near":0,"dead_cross":1,"dead_cross_near":13.0666666666669},"9766":{"golden_cross_near":0,"dead_cross":1,"price":13725,"end_date":"2025-01-23T06:30:00","golden_cross":0,"dead_cross_near":0},"4534":{"price":3325,"golden_cross":0,"end_date":"2025-01-23T06:30:00","golden_cross_near":0,"dead_cross":1,"dead_cross_near":3.55555555555536},"6572":{"dead_cross_near":0,"price":244,"end_date":"2025-01-23T06:30:00","golden_cross":1,"golden_cross_near":52.5777777777778,"dead_cross":0},"4662":{"dead_cross_near":83.8370370370371,"dead_cross":1,"golden_cross_near":0,"golden_cross":0,"end_date":"2025-01-23T06:30:00","price":1081},"7267":{"dead_cross_near":0,"golden_cross_near":38.1925925925925,"dead_cross":0,"price":1491.5,"golden_cross":1,"end_date":"2025-01-23T06:30:00"},"7740":{"dead_cross_near":27.4814814814818,"price":4265,"end_date":"2025-01-23T06:30:00","golden_cross":1,"golden_cross_near":0,"dead_cross":0},"4390":{"dead_cross_near":95.6444444444444,"price":2463,"golden_cross":0,"end_date":"2025-01-23T06:30:00","golden_cross_near":0,"dead_cross":1},"4538":{"dead_cross":1,"golden_cross_near":0,"golden_cross":0,"end_date":"2025-01-23T06:30:00","price":2367,"dead_cross_near":0},"2002":{"dead_cross_near":54.0740740740742,"dead_cross":1,"golden_cross_near":0,"end_date":"2025-01-23T06:30:00","golden_cross":0,"price":1767.5},"1887":{"price":492,"end_date":"2025-01-23T06:30:00","golden_cross":0,"golden_cross_near":0,"dead_cross":1,"dead_cross_near":81.4370370370371},"4658":{"golden_cross_near":68.5925925925926,"dead_cross":0,"price":1055,"golden_cross":1,"end_date":"2025-01-23T06:30:00","dead_cross_near":0},"6269":{"dead_cross_near":0,"golden_cross":1,"end_date":"2025-01-23T06:30:00","price":3385,"dead_cross":0,"golden_cross_near":8.88888888888889},"4373":{"dead_cross":1,"golden_cross_near":0,"end_date":"2025-01-23T06:30:00","golden_cross":0,"price":2378,"dead_cross_near":13.6592592592595},"2501":{"dead_cross":1,"golden_cross_near":0,"golden_cross":0,"end_date":"2025-01-23T06:30:00","price":6750,"dead_cross_near":0},"7717":{"dead_cross_near":0,"dead_cross":0,"golden_cross_near":27.1555555555556,"end_date":"2025-01-23T06:30:00","golden_cross":1,"price":2435},"7224":{"golden_cross":1,"end_date":"2025-01-23T06:30:00","price":1344,"dead_cross":0,"golden_cross_near":0,"dead_cross_near":94.1037037037038},"3916":{"dead_cross_near":2.41481481481464,"dead_cross":1,"golden_cross_near":0,"end_date":"2025-01-23T06:30:00","golden_cross":0,"price":2012},"6914":{"dead_cross_near":0,"golden_cross_near":96.2814814814816,"dead_cross":1,"price":1692,"golden_cross":0,"end_date":"2025-01-23T06:30:00"},"7962":{"dead_cross_near":87.0370370370371,"price":843,"golden_cross":0,"end_date":"2025-01-23T06:30:00","golden_cross_near":0,"dead_cross":1},"6264":{"golden_cross":1,"end_date":"2025-01-23T06:30:00","price":1726,"dead_cross":0,"golden_cross_near":0,"dead_cross_near":0},"9278":{"golden_cross":0,"end_date":"2025-01-23T06:30:00","price":1311,"dead_cross":1,"golden_cross_near":0,"dead_cross_near":0}}}